neopoint/__init__.py
neopoint/app.py
neopoint/common/__init__.py
neopoint/common/version.py
neopoint/exceptions.py
neopoint/http/__init__.py
neopoint/http/exceptions.py
neopoint/http/http_method.py
neopoint/http/http_status.py
neopoint/http/http_version.py
neopoint/http/message.py
neopoint/http/path_params.py
neopoint/http/path_pattern.py
neopoint/http/query_params.py
neopoint/http/request.py
neopoint/http/request_method.py
neopoint/http/response.py
neopoint/py.typed
neopoint/routing/__init__.py
neopoint/routing/exceptions.py
neopoint/routing/path.py
neopoint/routing/py.typed
neopoint/routing/router.py
neopoint/utils/__init__.py
neopoint/utils/test_client.py
neopoint/wsgi/__init__.py
neopoint/wsgi/exceptions.py
neopoint/wsgi/wsgi_environment_dto.py
neopoint/wsgi/wsgi_version.py
neopoint-0.0.1.dist-info/LICENSE
neopoint-0.0.1.dist-info/METADATA
neopoint-0.0.1.dist-info/WHEEL
neopoint-0.0.1.dist-info/RECORD
